hapag_lloyd_sdk/__init__.py
hapag_lloyd_sdk/api.py
hapag_lloyd_sdk/client.py
hapag_lloyd_sdk/models.py
tests/__init__.py
tests/test_api.py
hapag_lloyd_sdk-0.2.1.dist-info/METADATA
hapag_lloyd_sdk-0.2.1.dist-info/WHEEL
hapag_lloyd_sdk-0.2.1.dist-info/top_level.txt
hapag_lloyd_sdk-0.2.1.dist-info/RECORD
