Metadata-Version: 2.1
Name: hapag_lloyd_sdk
Version: 0.2.1
Summary: Community SDK for Hapag-Lloyd API
Home-page: https://github.com/gedankenfabrik/hapag_lloyd_sdk
Author: Aaron Frank
Author-email: aaron.frank@gedankenfabrik.de
Classifier: Programming Language :: Python :: 3
Classifier: License :: OSI Approved :: MIT License
Classifier: Operating System :: OS Independent
Requires-Python: >=3.6
Requires-Dist: requests
Requires-Dist: pydantic
